{"description": "", "tags": [], "size": {"height": 720, "width": 1280}, "objects": [{"id": 346747939, "classId": 1285799, "description": "", "geometryType": "polygon", "labelerLogin": "Raziajuthy", "createdAt": "2020-02-04T10:56:00.293Z", "updatedAt": "2020-03-02T09:25:36.363Z", "tags": [], "classTitle": "Vertical_formwork", "points": {"exterior": [[708, 245], [706, 238], [711, 228], [718, 224], [722, 228], [732, 232], [732, 235], [728, 235], [727, 248]], "interior": []}}, {"id": 346747938, "classId": 1285799, "description": "", "geometryType": "polygon", "labelerLogin": "Raziajuthy", "createdAt": "2020-02-04T10:56:00.293Z", "updatedAt": "2020-03-02T09:25:36.363Z", "tags": [], "classTitle": "Vertical_formwork", "points": {"exterior": [[727, 371], [712, 369], [669, 350], [670, 327], [664, 317], [675, 307], [726, 322]], "interior": []}}, {"id": 346747935, "classId": 1285799, "description": "", "geometryType": "polygon", "labelerLogin": "Raziajuthy", "createdAt": "2020-02-04T10:56:00.293Z", "updatedAt": "2020-03-02T09:25:36.363Z", "tags": [], "classTitle": "Vertical_formwork", "points": {"exterior": [[1185, 395], [1202, 341], [1224, 326], [1242, 336], [1233, 353], [1219, 382], [1207, 397]], "interior": []}}, {"id": 346747934, "classId": 1285799, "description": "", "geometryType": "polygon", "labelerLogin": "Raziajuthy", "createdAt": "2020-02-04T10:56:00.293Z", "updatedAt": "2020-03-02T09:25:36.363Z", "tags": [], "classTitle": "Vertical_formwork", "points": {"exterior": [[1175, 387], [1183, 351], [1172, 347], [1184, 323], [1199, 326], [1203, 328], [1200, 343], [1184, 394]], "interior": []}}, {"id": 346747933, "classId": 1285799, "description": "", "geometryType": "polygon", "labelerLogin": "Raziajuthy", "createdAt": "2020-02-04T10:56:00.293Z", "updatedAt": "2020-03-02T09:25:36.363Z", "tags": [], "classTitle": "Vertical_formwork", "points": {"exterior": [[1079, 366], [1087, 331], [1074, 326], [1078, 311], [1108, 298], [1121, 307], [1094, 322], [1083, 369]], "interior": []}}, {"id": 346747932, "classId": 1285799, "description": "", "geometryType": "polygon", "labelerLogin": "Raziajuthy", "createdAt": "2020-02-04T10:56:00.293Z", "updatedAt": "2020-03-02T09:25:36.363Z", "tags": [], "classTitle": "Vertical_formwork", "points": {"exterior": [[1084, 370], [1097, 324], [1123, 308], [1144, 314], [1128, 332], [1119, 366]], "interior": []}}, {"id": 346747931, "classId": 1285799, "description": "", "geometryType": "polygon", "labelerLogin": "Raziajuthy", "createdAt": "2020-02-04T10:56:00.293Z", "updatedAt": "2020-03-02T09:25:36.363Z", "tags": [], "classTitle": "Vertical_formwork", "points": {"exterior": [[1007, 352], [1014, 290], [1051, 269], [1071, 273], [1064, 287], [1049, 291], [1040, 344]], "interior": []}}, {"id": 346747930, "classId": 1285799, "description": "", "geometryType": "polygon", "labelerLogin": "Raziajuthy", "createdAt": "2020-02-04T10:56:00.293Z", "updatedAt": "2020-03-02T09:25:36.363Z", "tags": [], "classTitle": "Vertical_formwork", "points": {"exterior": [[964, 361], [966, 324], [988, 328], [982, 358]], "interior": []}}, {"id": 346747929, "classId": 1285799, "description": "", "geometryType": "polygon", "labelerLogin": "Raziajuthy", "createdAt": "2020-02-04T10:56:00.293Z", "updatedAt": "2020-03-02T09:25:36.363Z", "tags": [], "classTitle": "Vertical_formwork", "points": {"exterior": [[845, 415], [851, 362], [873, 355], [880, 355], [880, 361], [888, 362], [889, 373], [879, 375], [876, 406]], "interior": []}}, {"id": 346747926, "classId": 1285799, "description": "", "geometryType": "polygon", "labelerLogin": "Raziajuthy", "createdAt": "2020-02-04T10:56:00.293Z", "updatedAt": "2020-03-02T09:25:36.363Z", "tags": [], "classTitle": "Vertical_formwork", "points": {"exterior": [[526, 392], [526, 363], [522, 356], [531, 340], [534, 341], [534, 329], [543, 330], [545, 338], [547, 347], [562, 354], [567, 342], [571, 343], [574, 346], [571, 357], [581, 362], [584, 414], [574, 415]], "interior": []}}, {"id": 346747925, "classId": 1285799, "description": "", "geometryType": "polygon", "labelerLogin": "Raziajuthy", "createdAt": "2020-02-04T10:56:00.293Z", "updatedAt": "2020-03-02T09:25:36.363Z", "tags": [], "classTitle": "Vertical_formwork", "points": {"exterior": [[504, 322], [503, 295], [499, 287], [508, 282], [518, 283], [521, 291], [524, 291], [525, 297], [518, 301], [519, 324]], "interior": []}}, {"id": 346747924, "classId": 1285799, "description": "", "geometryType": "polygon", "labelerLogin": "Raziajuthy", "createdAt": "2020-02-04T10:56:00.293Z", "updatedAt": "2020-03-02T09:25:36.363Z", "tags": [], "classTitle": "Vertical_formwork", "points": {"exterior": [[459, 357], [457, 317], [501, 337], [500, 347]], "interior": []}}, {"id": 346747922, "classId": 1285799, "description": "", "geometryType": "polygon", "labelerLogin": "Raziajuthy", "createdAt": "2020-02-04T10:56:00.293Z", "updatedAt": "2020-03-02T09:25:36.363Z", "tags": [], "classTitle": "Vertical_formwork", "points": {"exterior": [[409, 316], [407, 284], [414, 284], [413, 278], [401, 272], [384, 280], [383, 290], [394, 294], [397, 311]], "interior": []}}, {"id": 346747921, "classId": 1285799, "description": "", "geometryType": "polygon", "labelerLogin": "Raziajuthy", "createdAt": "2020-02-04T10:56:00.293Z", "updatedAt": "2020-03-02T09:25:36.363Z", "tags": [], "classTitle": "Vertical_formwork", "points": {"exterior": [[416, 286], [420, 272], [476, 267], [489, 274], [489, 281], [487, 308], [485, 312], [450, 316], [447, 300]], "interior": []}}, {"id": 346747918, "classId": 1285799, "description": "", "geometryType": "polygon", "labelerLogin": "Raziajuthy", "createdAt": "2020-02-04T10:56:00.293Z", "updatedAt": "2020-03-02T09:25:36.363Z", "tags": [], "classTitle": "Vertical_formwork", "points": {"exterior": [[910, 304], [915, 273], [908, 271], [915, 264], [928, 264], [928, 273], [935, 275], [928, 279], [923, 298], [917, 305]], "interior": []}}, {"id": 346747916, "classId": 1285799, "description": "", "geometryType": "polygon", "labelerLogin": "Raziajuthy", "createdAt": "2020-02-04T10:56:00.293Z", "updatedAt": "2020-03-02T09:25:36.363Z", "tags": [], "classTitle": "Vertical_formwork", "points": {"exterior": [[872, 318], [872, 312], [878, 312], [882, 302], [911, 309], [909, 323]], "interior": []}}, {"id": 346747915, "classId": 1285799, "description": "", "geometryType": "polygon", "labelerLogin": "Raziajuthy", "createdAt": "2020-02-04T10:56:00.293Z", "updatedAt": "2020-03-02T09:25:36.363Z", "tags": [], "classTitle": "Vertical_formwork", "points": {"exterior": [[812, 358], [814, 342], [814, 336], [820, 321], [890, 345], [873, 351], [862, 355], [848, 361], [835, 365]], "interior": []}}, {"id": 346770976, "classId": 1285799, "description": "", "geometryType": "polygon", "labelerLogin": "Raziajuthy", "createdAt": "2020-02-04T11:02:42.596Z", "updatedAt": "2020-03-02T09:25:36.363Z", "tags": [], "classTitle": "Vertical_formwork", "points": {"exterior": [[757, 391], [760, 361], [754, 356], [763, 341], [838, 368], [829, 422]], "interior": []}}, {"id": 346770980, "classId": 1285811, "description": "", "geometryType": "rectangle", "labelerLogin": "Raziajuthy", "createdAt": "2020-02-04T11:02:55.882Z", "updatedAt": "2020-03-02T09:25:36.363Z", "tags": [], "classTitle": "People", "points": {"exterior": [[779, 322], [787, 338]], "interior": []}}, {"id": 346770985, "classId": 1285811, "description": "", "geometryType": "rectangle", "labelerLogin": "Raziajuthy", "createdAt": "2020-02-04T11:03:07.677Z", "updatedAt": "2020-03-02T09:25:36.363Z", "tags": [], "classTitle": "People", "points": {"exterior": [[787, 392], [798, 420]], "interior": []}}, {"id": 346771040, "classId": 1285811, "description": "", "geometryType": "rectangle", "labelerLogin": "Raziajuthy", "createdAt": "2020-02-04T11:04:56.358Z", "updatedAt": "2020-03-02T09:25:36.363Z", "tags": [], "classTitle": "People", "points": {"exterior": [[183, 439], [200, 461]], "interior": []}}, {"id": 346771080, "classId": 1285811, "description": "", "geometryType": "rectangle", "labelerLogin": "Raziajuthy", "createdAt": "2020-02-04T11:05:54.626Z", "updatedAt": "2020-03-02T09:25:36.363Z", "tags": [], "classTitle": "People", "points": {"exterior": [[699, 705], [718, 720]], "interior": []}}, {"id": 346771082, "classId": 1285811, "description": "", "geometryType": "rectangle", "labelerLogin": "Raziajuthy", "createdAt": "2020-02-04T11:05:59.562Z", "updatedAt": "2020-03-02T09:25:36.363Z", "tags": [], "classTitle": "People", "points": {"exterior": [[689, 677], [708, 720]], "interior": []}}, {"id": 346771195, "classId": 1285799, "description": "", "geometryType": "polygon", "labelerLogin": "Raziajuthy", "createdAt": "2020-02-04T11:08:50.216Z", "updatedAt": "2020-03-02T09:25:36.363Z", "tags": [], "classTitle": "Vertical_formwork", "points": {"exterior": [[1232, 432], [1261, 361], [1277, 352], [1279, 371], [1280, 420]], "interior": []}}, {"id": 347455578, "classId": 1285811, "description": "", "geometryType": "rectangle", "labelerLogin": "sujon", "createdAt": "2020-02-06T07:36:21.839Z", "updatedAt": "2020-03-02T09:25:36.363Z", "tags": [], "classTitle": "People", "points": {"exterior": [[42, 367], [48, 383]], "interior": []}}, {"id": 365419386, "classId": 1285799, "description": "", "geometryType": "polygon", "labelerLogin": "Raziajuthy", "createdAt": "2020-03-02T09:25:36.363Z", "updatedAt": "2020-03-02T09:25:36.363Z", "tags": [], "classTitle": "Vertical_formwork", "points": {"exterior": [[1171, 588], [1188, 546], [1239, 534], [1279, 555], [1279, 640], [1261, 645]], "interior": []}}]}