{"description": "", "tags": [], "size": {"height": 1080, "width": 1616}, "objects": [{"id": 347018186, "classId": 1285811, "description": "", "geometryType": "rectangle", "labelerLogin": "mustakim", "createdAt": "2020-02-05T06:04:50.960Z", "updatedAt": "2020-03-02T11:43:10.139Z", "tags": [], "classTitle": "People", "points": {"exterior": [[590, 982], [599, 995]], "interior": []}}, {"id": 347018200, "classId": 1285799, "description": "", "geometryType": "polygon", "labelerLogin": "mustakim", "createdAt": "2020-02-05T06:04:57.137Z", "updatedAt": "2020-03-02T11:43:10.139Z", "tags": [], "classTitle": "Vertical_formwork", "points": {"exterior": [[598, 1016], [605, 999], [575, 987], [583, 960], [538, 941], [501, 919], [462, 892], [419, 855], [375, 809], [348, 765], [328, 716], [315, 666], [302, 645], [302, 631], [286, 621], [287, 636], [256, 622], [260, 672], [282, 741], [315, 803], [377, 880], [430, 928], [486, 963], [532, 992]], "interior": []}}, {"id": 347018468, "classId": 1285811, "description": "", "geometryType": "rectangle", "labelerLogin": "mustakim", "createdAt": "2020-02-05T06:07:19.244Z", "updatedAt": "2020-03-02T11:43:10.139Z", "tags": [], "classTitle": "People", "points": {"exterior": [[596, 636], [607, 649]], "interior": []}}, {"id": 347018474, "classId": 1285811, "description": "", "geometryType": "rectangle", "labelerLogin": "mustakim", "createdAt": "2020-02-05T06:07:23.667Z", "updatedAt": "2020-03-02T11:43:10.139Z", "tags": [], "classTitle": "People", "points": {"exterior": [[447, 597], [461, 611]], "interior": []}}]}