{"description": "", "tags": [], "size": {"height": 1080, "width": 1616}, "objects": [{"id": 347017567, "classId": 1285811, "description": "", "geometryType": "rectangle", "labelerLogin": "jessie", "createdAt": "2020-02-05T06:00:28.466Z", "updatedAt": "2020-03-03T12:32:15.684Z", "tags": [], "classTitle": "People", "points": {"exterior": [[1426, 725], [1463, 747]], "interior": []}}, {"id": 347017829, "classId": 1285811, "description": "", "geometryType": "rectangle", "labelerLogin": "jessie", "createdAt": "2020-02-05T06:02:22.279Z", "updatedAt": "2020-03-03T12:32:15.684Z", "tags": [], "classTitle": "People", "points": {"exterior": [[885, 455], [890, 469]], "interior": []}}, {"id": 347017901, "classId": 1285811, "description": "", "geometryType": "rectangle", "labelerLogin": "jessie", "createdAt": "2020-02-05T06:02:50.305Z", "updatedAt": "2020-03-03T12:32:15.684Z", "tags": [], "classTitle": "People", "points": {"exterior": [[567, 583], [577, 592]], "interior": []}}, {"id": 347018016, "classId": 1285811, "description": "", "geometryType": "rectangle", "labelerLogin": "jessie", "createdAt": "2020-02-05T06:03:32.395Z", "updatedAt": "2020-03-03T12:32:15.684Z", "tags": [], "classTitle": "People", "points": {"exterior": [[645, 481], [657, 497]], "interior": []}}, {"id": 347018039, "classId": 1285811, "description": "", "geometryType": "rectangle", "labelerLogin": "jessie", "createdAt": "2020-02-05T06:03:36.183Z", "updatedAt": "2020-03-03T12:32:15.684Z", "tags": [], "classTitle": "People", "points": {"exterior": [[665, 484], [675, 501]], "interior": []}}, {"id": 347018078, "classId": 1285811, "description": "", "geometryType": "rectangle", "labelerLogin": "jessie", "createdAt": "2020-02-05T06:03:56.263Z", "updatedAt": "2020-03-03T12:32:15.684Z", "tags": [], "classTitle": "People", "points": {"exterior": [[673, 445], [680, 462]], "interior": []}}, {"id": 347018086, "classId": 1285811, "description": "", "geometryType": "rectangle", "labelerLogin": "jessie", "createdAt": "2020-02-05T06:04:00.377Z", "updatedAt": "2020-03-03T12:32:15.684Z", "tags": [], "classTitle": "People", "points": {"exterior": [[697, 442], [704, 451]], "interior": []}}, {"id": 347018115, "classId": 1285811, "description": "", "geometryType": "rectangle", "labelerLogin": "jessie", "createdAt": "2020-02-05T06:04:17.052Z", "updatedAt": "2020-03-03T12:32:15.684Z", "tags": [], "classTitle": "People", "points": {"exterior": [[688, 444], [698, 462]], "interior": []}}, {"id": 347018169, "classId": 1285811, "description": "", "geometryType": "rectangle", "labelerLogin": "jessie", "createdAt": "2020-02-05T06:04:44.413Z", "updatedAt": "2020-03-03T12:32:15.684Z", "tags": [], "classTitle": "People", "points": {"exterior": [[701, 407], [710, 419]], "interior": []}}, {"id": 347018298, "classId": 1285811, "description": "", "geometryType": "rectangle", "labelerLogin": "jessie", "createdAt": "2020-02-05T06:05:39.252Z", "updatedAt": "2020-03-03T12:32:15.684Z", "tags": [], "classTitle": "People", "points": {"exterior": [[681, 424], [688, 434]], "interior": []}}, {"id": 347018326, "classId": 1285811, "description": "", "geometryType": "rectangle", "labelerLogin": "jessie", "createdAt": "2020-02-05T06:05:53.154Z", "updatedAt": "2020-03-03T12:32:15.684Z", "tags": [], "classTitle": "People", "points": {"exterior": [[671, 425], [680, 435]], "interior": []}}, {"id": 347018344, "classId": 1285811, "description": "", "geometryType": "rectangle", "labelerLogin": "jessie", "createdAt": "2020-02-05T06:06:01.955Z", "updatedAt": "2020-03-03T12:32:15.684Z", "tags": [], "classTitle": "People", "points": {"exterior": [[670, 414], [678, 425]], "interior": []}}, {"id": 347018376, "classId": 1285811, "description": "", "geometryType": "rectangle", "labelerLogin": "jessie", "createdAt": "2020-02-05T06:06:18.481Z", "updatedAt": "2020-03-03T12:32:15.684Z", "tags": [], "classTitle": "People", "points": {"exterior": [[669, 394], [674, 404]], "interior": []}}, {"id": 347018391, "classId": 1285811, "description": "", "geometryType": "rectangle", "labelerLogin": "jessie", "createdAt": "2020-02-05T06:06:27.118Z", "updatedAt": "2020-03-03T12:32:15.684Z", "tags": [], "classTitle": "People", "points": {"exterior": [[624, 428], [635, 439]], "interior": []}}, {"id": 347023023, "classId": 1285811, "description": "", "geometryType": "rectangle", "labelerLogin": "jessie", "createdAt": "2020-02-05T06:07:51.991Z", "updatedAt": "2020-03-03T12:32:15.684Z", "tags": [], "classTitle": "People", "points": {"exterior": [[822, 827], [834, 839]], "interior": []}}, {"id": 347023025, "classId": 1285811, "description": "", "geometryType": "rectangle", "labelerLogin": "jessie", "createdAt": "2020-02-05T06:07:54.977Z", "updatedAt": "2020-03-03T12:32:15.684Z", "tags": [], "classTitle": "People", "points": {"exterior": [[846, 829], [861, 839]], "interior": []}}, {"id": 347023032, "classId": 1285811, "description": "", "geometryType": "rectangle", "labelerLogin": "jessie", "createdAt": "2020-02-05T06:07:58.609Z", "updatedAt": "2020-03-03T12:32:15.684Z", "tags": [], "classTitle": "People", "points": {"exterior": [[827, 861], [840, 875]], "interior": []}}, {"id": 347023057, "classId": 1285811, "description": "", "geometryType": "rectangle", "labelerLogin": "jessie", "createdAt": "2020-02-05T06:08:15.555Z", "updatedAt": "2020-03-03T12:32:15.684Z", "tags": [], "classTitle": "People", "points": {"exterior": [[802, 850], [813, 861]], "interior": []}}, {"id": 347023064, "classId": 1285811, "description": "", "geometryType": "rectangle", "labelerLogin": "jessie", "createdAt": "2020-02-05T06:08:19.058Z", "updatedAt": "2020-03-03T12:32:15.684Z", "tags": [], "classTitle": "People", "points": {"exterior": [[769, 844], [781, 861]], "interior": []}}, {"id": 348738341, "classId": 1285811, "description": "", "geometryType": "rectangle", "labelerLogin": "Raziajuthy", "createdAt": "2020-02-09T05:07:36.205Z", "updatedAt": "2020-03-03T12:32:15.684Z", "tags": [], "classTitle": "People", "points": {"exterior": [[913, 536], [920, 549]], "interior": []}}]}