{"description": "", "tags": [], "size": {"height": 720, "width": 1280}, "objects": [{"id": 345520249, "classId": 1285799, "description": "", "geometryType": "polygon", "labelerLogin": "jeba", "createdAt": "2020-01-31T05:51:20.491Z", "updatedAt": "2020-02-08T05:58:02.675Z", "tags": [], "classTitle": "Vertical_formwork", "points": {"exterior": [[822, 422], [822, 405], [828, 391], [839, 373], [856, 377], [861, 367], [867, 368], [870, 379], [876, 379], [884, 368], [890, 367], [904, 375], [906, 383], [923, 383], [919, 368], [927, 367], [929, 383], [983, 382], [1047, 426], [1042, 440], [1027, 500], [1016, 502], [965, 498], [891, 489], [887, 467], [821, 466]], "interior": []}}, {"id": 345520246, "classId": 1285799, "description": "", "geometryType": "polygon", "labelerLogin": "jeba", "createdAt": "2020-01-31T05:51:20.491Z", "updatedAt": "2020-02-08T05:44:54.134Z", "tags": [], "classTitle": "Vertical_formwork", "points": {"exterior": [[770, 361], [766, 373], [792, 374], [794, 375], [822, 377], [823, 374], [818, 371], [814, 357], [802, 355]], "interior": []}}, {"id": 345520245, "classId": 1285799, "description": "", "geometryType": "polygon", "labelerLogin": "jeba", "createdAt": "2020-01-31T05:51:20.491Z", "updatedAt": "2020-02-08T05:44:54.134Z", "tags": [], "classTitle": "Vertical_formwork", "points": {"exterior": [[762, 380], [751, 380], [752, 337], [768, 336], [770, 353], [762, 352]], "interior": []}}, {"id": 345520244, "classId": 1285799, "description": "", "geometryType": "polygon", "labelerLogin": "jeba", "createdAt": "2020-01-31T05:51:20.491Z", "updatedAt": "2020-02-08T05:44:54.134Z", "tags": [], "classTitle": "Vertical_formwork", "points": {"exterior": [[798, 433], [802, 433], [811, 431], [814, 423], [816, 426], [816, 434], [821, 435], [821, 394], [821, 386], [824, 378], [793, 375], [786, 383], [788, 403], [792, 405], [792, 432]], "interior": []}}, {"id": 345520386, "classId": 1285811, "description": "", "geometryType": "rectangle", "labelerLogin": "jeba", "createdAt": "2020-01-31T05:52:21.913Z", "updatedAt": "2020-02-08T05:44:54.134Z", "tags": [], "classTitle": "People", "points": {"exterior": [[284, 412], [299, 442]], "interior": []}}, {"id": 345520406, "classId": 1285811, "description": "", "geometryType": "rectangle", "labelerLogin": "jeba", "createdAt": "2020-01-31T05:52:39.676Z", "updatedAt": "2020-02-08T05:44:54.134Z", "tags": [], "classTitle": "People", "points": {"exterior": [[252, 466], [280, 490]], "interior": []}}, {"id": 345520491, "classId": 1285804, "description": "", "geometryType": "polygon", "labelerLogin": "jeba", "createdAt": "2020-01-31T05:53:44.726Z", "updatedAt": "2020-02-18T12:05:42.812Z", "tags": [], "classTitle": "Concrete_pump_hose", "points": {"exterior": [[150, 214], [291, 360], [312, 385], [313, 397], [312, 410], [309, 419], [305, 428], [303, 433], [301, 438], [305, 438], [311, 428], [317, 417], [320, 400], [321, 393], [320, 383], [312, 371], [304, 362], [272, 323], [155, 195], [0, 152], [0, 167]], "interior": []}}]}