{"description": "", "tags": [], "size": {"height": 1080, "width": 1616}, "objects": [{"id": 347118158, "classId": 1285811, "description": "", "geometryType": "rectangle", "labelerLogin": "Bijoy", "createdAt": "2020-02-05T10:49:31.125Z", "updatedAt": "2020-03-02T12:32:50.219Z", "tags": [], "classTitle": "People", "points": {"exterior": [[567, 293], [577, 312]], "interior": []}}, {"id": 347118167, "classId": 1285811, "description": "", "geometryType": "rectangle", "labelerLogin": "Bijoy", "createdAt": "2020-02-05T10:49:37.841Z", "updatedAt": "2020-03-02T12:32:50.219Z", "tags": [], "classTitle": "People", "points": {"exterior": [[574, 291], [583, 310]], "interior": []}}, {"id": 347118194, "classId": 1285811, "description": "", "geometryType": "rectangle", "labelerLogin": "Bijoy", "createdAt": "2020-02-05T10:49:55.441Z", "updatedAt": "2020-03-02T12:32:50.219Z", "tags": [], "classTitle": "People", "points": {"exterior": [[787, 186], [794, 197]], "interior": []}}, {"id": 347118219, "classId": 1285811, "description": "", "geometryType": "rectangle", "labelerLogin": "Bijoy", "createdAt": "2020-02-05T10:50:07.809Z", "updatedAt": "2020-03-02T12:32:50.219Z", "tags": [], "classTitle": "People", "points": {"exterior": [[612, 227], [619, 240]], "interior": []}}, {"id": 347118277, "classId": 1285811, "description": "", "geometryType": "rectangle", "labelerLogin": "Bijoy", "createdAt": "2020-02-05T10:50:46.429Z", "updatedAt": "2020-03-02T12:32:50.219Z", "tags": [], "classTitle": "People", "points": {"exterior": [[964, 498], [974, 515]], "interior": []}}, {"id": 347118297, "classId": 1285811, "description": "", "geometryType": "rectangle", "labelerLogin": "Bijoy", "createdAt": "2020-02-05T10:50:58.603Z", "updatedAt": "2020-03-02T12:32:50.219Z", "tags": [], "classTitle": "People", "points": {"exterior": [[1062, 683], [1073, 695]], "interior": []}}, {"id": 347118303, "classId": 1285811, "description": "", "geometryType": "rectangle", "labelerLogin": "Bijoy", "createdAt": "2020-02-05T10:51:05.765Z", "updatedAt": "2020-03-02T12:32:50.219Z", "tags": [], "classTitle": "People", "points": {"exterior": [[1291, 479], [1301, 494]], "interior": []}}, {"id": 347118311, "classId": 1285811, "description": "", "geometryType": "rectangle", "labelerLogin": "Bijoy", "createdAt": "2020-02-05T10:51:11.234Z", "updatedAt": "2020-03-02T12:32:50.219Z", "tags": [], "classTitle": "People", "points": {"exterior": [[1349, 554], [1363, 569]], "interior": []}}, {"id": 347118334, "classId": 1285811, "description": "", "geometryType": "rectangle", "labelerLogin": "Bijoy", "createdAt": "2020-02-05T10:51:30.228Z", "updatedAt": "2020-03-02T12:32:50.219Z", "tags": [], "classTitle": "People", "points": {"exterior": [[1178, 829], [1196, 845]], "interior": []}}, {"id": 347118344, "classId": 1285811, "description": "", "geometryType": "rectangle", "labelerLogin": "Bijoy", "createdAt": "2020-02-05T10:51:38.408Z", "updatedAt": "2020-03-02T12:32:50.219Z", "tags": [], "classTitle": "People", "points": {"exterior": [[839, 918], [849, 933]], "interior": []}}, {"id": 348739199, "classId": 1285811, "description": "", "geometryType": "rectangle", "labelerLogin": "almahadi87", "createdAt": "2020-02-09T05:53:36.632Z", "updatedAt": "2020-03-02T12:32:50.219Z", "tags": [], "classTitle": "People", "points": {"exterior": [[1397, 555], [1422, 573]], "interior": []}}]}