{"description": "", "tags": [], "size": {"height": 720, "width": 1280}, "objects": [{"id": 344149599, "classId": 1285809, "description": "", "geometryType": "rectangle", "labelerLogin": "jeba", "createdAt": "2020-01-29T05:33:07.598Z", "updatedAt": "2020-02-06T05:37:55.759Z", "tags": [], "classTitle": "Mixer_truck", "points": {"exterior": [[0, 412], [289, 720]], "interior": []}}, {"id": 344149598, "classId": 1285799, "description": "", "geometryType": "polygon", "labelerLogin": "jeba", "createdAt": "2020-01-29T05:33:07.598Z", "updatedAt": "2020-02-06T05:37:55.759Z", "tags": [], "classTitle": "Vertical_formwork", "points": {"exterior": [[414, 467], [380, 462], [371, 460], [369, 411], [406, 399], [415, 409], [411, 418], [404, 418], [405, 437], [416, 437], [420, 463]], "interior": []}}, {"id": 344149597, "classId": 1285799, "description": "", "geometryType": "polygon", "labelerLogin": "jeba", "createdAt": "2020-01-29T05:33:07.598Z", "updatedAt": "2020-02-06T05:37:55.759Z", "tags": [], "classTitle": "Vertical_formwork", "points": {"exterior": [[305, 387], [304, 400], [330, 403], [345, 405], [354, 397], [353, 392], [350, 382], [342, 377], [328, 378], [325, 376], [320, 378], [317, 385]], "interior": []}}, {"id": 344149596, "classId": 1285799, "description": "", "geometryType": "polygon", "labelerLogin": "jeba", "createdAt": "2020-01-29T05:33:07.598Z", "updatedAt": "2020-02-06T05:37:55.759Z", "tags": [], "classTitle": "Vertical_formwork", "points": {"exterior": [[531, 386], [513, 387], [515, 354], [535, 350], [545, 349], [554, 349], [564, 353], [562, 378], [550, 378], [541, 377], [531, 378]], "interior": []}}, {"id": 344149595, "classId": 1285799, "description": "", "geometryType": "polygon", "labelerLogin": "jeba", "createdAt": "2020-01-29T05:33:07.598Z", "updatedAt": "2020-02-06T05:37:55.759Z", "tags": [], "classTitle": "Vertical_formwork", "points": {"exterior": [[750, 379], [752, 366], [756, 364], [808, 365], [809, 379], [809, 400], [805, 400], [804, 380]], "interior": []}}, {"id": 344149594, "classId": 1285799, "description": "", "geometryType": "polygon", "labelerLogin": "jeba", "createdAt": "2020-01-29T05:33:07.598Z", "updatedAt": "2020-02-06T05:37:55.759Z", "tags": [], "classTitle": "Vertical_formwork", "points": {"exterior": [[751, 371], [725, 370], [719, 363], [720, 356], [732, 356], [732, 353], [736, 353], [736, 349], [743, 349], [742, 345], [746, 345], [750, 346], [759, 347], [767, 352], [777, 355], [777, 359], [773, 364], [756, 364], [752, 366]], "interior": []}}, {"id": 344149593, "classId": 1285799, "description": "", "geometryType": "polygon", "labelerLogin": "jeba", "createdAt": "2020-01-29T05:33:07.598Z", "updatedAt": "2020-02-06T05:37:55.759Z", "tags": [], "classTitle": "Vertical_formwork", "points": {"exterior": [[391, 392], [393, 380], [406, 374], [417, 377], [416, 381], [421, 384], [420, 389], [422, 398], [417, 401], [417, 409], [414, 409], [413, 394]], "interior": []}}, {"id": 344149592, "classId": 1285799, "description": "", "geometryType": "polygon", "labelerLogin": "jeba", "createdAt": "2020-01-29T05:33:07.598Z", "updatedAt": "2020-02-06T05:37:55.759Z", "tags": [], "classTitle": "Vertical_formwork", "points": {"exterior": [[411, 371], [410, 356], [418, 356], [418, 367], [417, 369]], "interior": []}}, {"id": 344149591, "classId": 1285799, "description": "", "geometryType": "polygon", "labelerLogin": "jeba", "createdAt": "2020-01-29T05:33:07.598Z", "updatedAt": "2020-02-06T05:37:55.759Z", "tags": [], "classTitle": "Vertical_formwork", "points": {"exterior": [[448, 362], [449, 357], [455, 355], [460, 360], [459, 371], [456, 371], [456, 379], [449, 378], [448, 369]], "interior": []}}, {"id": 344149590, "classId": 1285799, "description": "", "geometryType": "polygon", "labelerLogin": "jeba", "createdAt": "2020-01-29T05:33:07.598Z", "updatedAt": "2020-02-06T05:37:55.759Z", "tags": [], "classTitle": "Vertical_formwork", "points": {"exterior": [[432, 365], [439, 365], [440, 364], [444, 364], [445, 357], [441, 352], [435, 352], [432, 358]], "interior": []}}, {"id": 344149589, "classId": 1285799, "description": "", "geometryType": "polygon", "labelerLogin": "jeba", "createdAt": "2020-01-29T05:33:07.598Z", "updatedAt": "2020-02-06T05:37:55.759Z", "tags": [], "classTitle": "Vertical_formwork", "points": {"exterior": [[618, 372], [620, 375], [642, 374], [643, 378], [660, 372], [659, 362], [666, 361], [666, 350], [644, 338], [638, 340], [637, 345], [631, 347], [631, 341], [625, 342], [622, 361]], "interior": []}}, {"id": 344149675, "classId": 1285811, "description": "", "geometryType": "rectangle", "labelerLogin": "jeba", "createdAt": "2020-01-29T05:34:03.018Z", "updatedAt": "2020-02-06T05:37:55.759Z", "tags": [], "classTitle": "People", "points": {"exterior": [[962, 448], [979, 496]], "interior": []}}, {"id": 344149689, "classId": 1285811, "description": "", "geometryType": "rectangle", "labelerLogin": "jeba", "createdAt": "2020-01-29T05:34:14.442Z", "updatedAt": "2020-02-06T05:37:55.759Z", "tags": [], "classTitle": "People", "points": {"exterior": [[1001, 444], [1030, 471]], "interior": []}}, {"id": 344149704, "classId": 1285811, "description": "", "geometryType": "rectangle", "labelerLogin": "jeba", "createdAt": "2020-01-29T05:34:27.313Z", "updatedAt": "2020-02-06T05:37:55.759Z", "tags": [], "classTitle": "People", "points": {"exterior": [[1059, 478], [1086, 509]], "interior": []}}, {"id": 344149743, "classId": 1285811, "description": "", "geometryType": "rectangle", "labelerLogin": "jeba", "createdAt": "2020-01-29T05:34:56.418Z", "updatedAt": "2020-02-06T05:37:55.759Z", "tags": [], "classTitle": "People", "points": {"exterior": [[1184, 603], [1221, 651]], "interior": []}}, {"id": 344149847, "classId": 1285811, "description": "", "geometryType": "rectangle", "labelerLogin": "jeba", "createdAt": "2020-01-29T05:35:26.166Z", "updatedAt": "2020-02-06T05:37:55.759Z", "tags": [], "classTitle": "People", "points": {"exterior": [[1117, 593], [1151, 644]], "interior": []}}, {"id": 344151651, "classId": 1285811, "description": "", "geometryType": "rectangle", "labelerLogin": "jeba", "createdAt": "2020-01-29T05:41:50.794Z", "updatedAt": "2020-02-06T05:37:55.759Z", "tags": [], "classTitle": "People", "points": {"exterior": [[451, 477], [467, 500]], "interior": []}}, {"id": 344155867, "classId": 1285799, "description": "", "geometryType": "polygon", "labelerLogin": "jeba", "createdAt": "2020-01-29T06:10:15.535Z", "updatedAt": "2020-02-06T05:37:55.759Z", "tags": [], "classTitle": "Vertical_formwork", "points": {"exterior": [[720, 356], [719, 310], [726, 306], [730, 309], [752, 310], [756, 315], [755, 319], [753, 321], [754, 346], [752, 346], [746, 345], [742, 345], [743, 349], [736, 349], [736, 353], [732, 353], [732, 356]], "interior": []}}, {"id": 344161876, "classId": 1285799, "description": "", "geometryType": "polygon", "labelerLogin": "jeba", "createdAt": "2020-01-29T06:44:07.315Z", "updatedAt": "2020-02-06T05:37:55.759Z", "tags": [], "classTitle": "Vertical_formwork", "points": {"exterior": [[201, 379], [200, 388], [205, 389], [213, 394], [246, 387], [251, 387], [251, 399], [258, 397], [257, 384], [271, 381], [263, 374], [251, 371], [236, 371], [235, 375]], "interior": []}}, {"id": 347437242, "classId": 1285799, "description": "", "geometryType": "polygon", "labelerLogin": "nafiz", "createdAt": "2020-02-06T05:37:20.075Z", "updatedAt": "2020-02-06T05:37:55.759Z", "tags": [], "classTitle": "Vertical_formwork", "points": {"exterior": [[819, 350], [820, 360], [828, 370], [834, 376], [840, 377], [841, 372], [851, 372], [852, 377], [859, 377], [861, 360], [857, 357], [855, 350]], "interior": []}}, {"id": 347437290, "classId": 1285809, "description": "", "geometryType": "rectangle", "labelerLogin": "nafiz", "createdAt": "2020-02-06T05:37:55.402Z", "updatedAt": "2020-02-06T05:37:55.402Z", "tags": [], "classTitle": "Mixer_truck", "points": {"exterior": [[914, 593], [1278, 717]], "interior": []}}]}